fotofriend/__init__.py
fotofriend-1.0.4.dist-info/DESCRIPTION.rst
fotofriend-1.0.4.dist-info/METADATA
fotofriend-1.0.4.dist-info/RECORD
fotofriend-1.0.4.dist-info/WHEEL
fotofriend-1.0.4.dist-info/metadata.json
fotofriend-1.0.4.dist-info/top_level.txt
