Metadata-Version: 2.0
Name: fotofriend
Version: 1.0.4
Summary: Python Binding for FotoFriend
Home-page: https://github.com/dsecca/FotoFriend_LanguageBinding
Author: FotoFriend
Author-email: fotofriendtest@gmail.com
License: MIT
Keywords: fotofriend setuptools development filtering images
Platform: UNKNOWN
Classifier: Development Status :: 5 - Production/Stable
Classifier: Intended Audience :: Developers
Classifier: Topic :: Software Development :: Build Tools
Classifier: License :: OSI Approved :: MIT License
Classifier: Programming Language :: Python :: 2
Classifier: Programming Language :: Python :: 2.7
Classifier: Programming Language :: Python :: 3
Classifier: Programming Language :: Python :: 3.3
Classifier: Programming Language :: Python :: 3.4
Requires-Dist: requests
